[
  {
    "type": "fix",
    "scope": null,
    "subject": "rm child prepack in favour of root prepack",
    "merge": null,
    "header": "fix: rm child prepack in favour of root prepack",
    "body": null,
    "footer": null,
    "notes": [],
    "hash": "381d8d6485269b641d8d4655148966d2e70803be",
    "gitTags": "",
    "committerDate": "2019-03-15 09:51:11 +0000",
    "isTagged": true,
    "tag": "@pie-lib/text-select@1.4.9"
  },
  {
    "type": "chore",
    "scope": null,
    "subject": "get packages to call changelog function on prepack",
    "merge": null,
    "header": "chore: get packages to call changelog function on prepack",
    "body": null,
    "footer": null,
    "notes": [],
    "hash": "8828f01f2d16d29404ba837c1de40d09e7230ec5",
    "gitTags": "",
    "committerDate": "2019-03-14 12:40:05 +0000",
    "isTagged": true,
    "tag": "@pie-lib/text-select@1.4.5"
  },
  {
    "type": "chore",
    "scope": null,
    "subject": "call changelog on prepack",
    "merge": null,
    "header": "chore: call changelog on prepack",
    "body": null,
    "footer": null,
    "notes": [],
    "hash": "b672c012de096c55b765a765f758da3fc5df2f90",
    "gitTags": "",
    "committerDate": "2019-03-13 23:00:44 +0000",
    "isTagged": true,
    "tag": "@pie-lib/text-select@1.4.4"
  },
  {
    "type": "chore",
    "scope": null,
    "subject": "generate changelog.json instead of markdown",
    "merge": null,
    "header": "chore: generate changelog.json instead of markdown",
    "body": null,
    "footer": null,
    "notes": [],
    "hash": "eaa5019a11f70c53425d55856bd3b940237f8c7d",
    "gitTags": "",
    "committerDate": "2019-03-13 17:24:09 +0000",
    "isTagged": true,
    "tag": "@pie-lib/text-select@1.4.2"
  },
  {
    "type": "fix",
    "scope": null,
    "subject": "fix tests",
    "merge": null,
    "header": "fix: fix tests",
    "body": null,
    "footer": null,
    "notes": [],
    "hash": "1363aa4540f970c8cdd05ef05c1325de973d22e2",
    "gitTags": "",
    "committerDate": "2019-02-16 23:47:25 +0000",
    "isTagged": true,
    "tag": "@pie-lib/text-select@1.4.1"
  },
  {
    "type": "feat",
    "scope": null,
    "subject": "support html markup in TextSelect",
    "merge": null,
    "header": "feat: support html markup in TextSelect",
    "body": "text-select only worked with plain text when rendering because it used\nsafe rendering. This change now does markup up rendering.",
    "footer": null,
    "notes": [],
    "hash": "b3942ed811b05f57e585523a0bac06b0c2f039ce",
    "gitTags": "",
    "committerDate": "2019-02-07 15:24:36 +0000",
    "isTagged": true,
    "tag": "@pie-lib/text-select@1.4.0"
  },
  {
    "type": "feat",
    "scope": null,
    "subject": "libs version bump",
    "merge": null,
    "header": "feat: libs version bump",
    "body": null,
    "footer": null,
    "notes": [],
    "hash": "b4c1087c59eaa6a2d67fffec59fa288ecc68de9b",
    "gitTags": "",
    "committerDate": "2019-01-30 22:14:28 +0000",
    "isTagged": true,
    "tag": "@pie-lib/text-select@1.3.0"
  },
  {
    "type": "fix",
    "scope": "added-dependencies-where-needed",
    "subject": "fixed missing dependencies",
    "merge": null,
    "header": "fix(added-dependencies-where-needed): fixed missing dependencies",
    "body": null,
    "footer": null,
    "notes": [],
    "hash": "7c28bd3f42f7f5803bb9514c9f45d9540a024eb9",
    "gitTags": " (origin/fix/added-dependencies-where-needed)",
    "committerDate": "2018-11-09 16:44:05 +0200",
    "isTagged": true,
    "tag": "@pie-lib/text-select@1.2.3"
  },
  {
    "type": "fix",
    "scope": "mode-save",
    "subject": "added some tests and refactored some code",
    "merge": null,
    "header": "fix(mode-save): added some tests and refactored some code",
    "body": null,
    "footer": null,
    "notes": [],
    "hash": "2ffeaca5ddb0abe1e33c8b11b7a6928cd9ee7368",
    "gitTags": "",
    "committerDate": "2018-10-16 12:00:59 +0300",
    "isTagged": true,
    "tag": "@pie-lib/text-select@1.2.2"
  },
  {
    "type": "fix",
    "scope": "mode-save",
    "subject": "added a new state variable that saves the current mode of the tokenizer",
    "merge": null,
    "header": "fix(mode-save): added a new state variable that saves the current mode of the tokenizer",
    "body": null,
    "footer": null,
    "notes": [],
    "hash": "340b4bab2aafade4933c25d877a6a74385684568",
    "gitTags": "",
    "committerDate": "2018-10-15 12:33:16 +0300",
    "isTagged": true,
    "tag": "@pie-lib/text-select@1.2.2"
  },
  {
    "type": "fix",
    "scope": "add-paragraph",
    "subject": "added a paragraph builder for tokens",
    "merge": null,
    "header": "fix(add-paragraph): added a paragraph builder for tokens",
    "body": null,
    "footer": null,
    "notes": [],
    "hash": "61189c05fbe5ed1f83a739a1a7734cc2bb016944",
    "gitTags": "",
    "committerDate": "2018-10-12 16:40:12 +0300",
    "isTagged": true,
    "tag": "@pie-lib/text-select@1.2.2"
  },
  {
    "type": "chore",
    "scope": null,
    "subject": "fix tests",
    "merge": null,
    "header": "chore: fix tests",
    "body": null,
    "footer": null,
    "notes": [],
    "hash": "274ab3bdb02b7a1738a861dc7594ca9392943e50",
    "gitTags": "",
    "committerDate": "2018-07-25 10:23:50 -0400",
    "isTagged": true,
    "tag": "@pie-lib/text-select@1.2.1"
  },
  {
    "type": "feat",
    "scope": null,
    "subject": "upgrade material-ui -> @material-ui/core@^1.0.0-rc.1",
    "merge": null,
    "header": "feat: upgrade material-ui -> @material-ui/core@^1.0.0-rc.1",
    "body": null,
    "footer": null,
    "notes": [],
    "hash": "017ef6300f1fd345fc932496d25682a7981a4938",
    "gitTags": "",
    "committerDate": "2018-05-15 21:52:09 -0400",
    "isTagged": true,
    "tag": "@pie-lib/text-select@1.2.0"
  },
  {
    "type": "fix",
    "scope": "lint",
    "subject": "lint fixes",
    "merge": null,
    "header": "fix(lint): lint fixes",
    "body": null,
    "footer": null,
    "notes": [],
    "hash": "f0595831a75561d829c0f18f86ce5ea7feeb4ddd",
    "gitTags": "",
    "committerDate": "2018-05-09 13:35:42 -0400",
    "isTagged": true,
    "tag": "@pie-lib/text-select@1.1.2"
  },
  {
    "type": "fix",
    "scope": "test",
    "subject": "fix test run",
    "merge": null,
    "header": "fix(test): fix test run",
    "body": null,
    "footer": null,
    "notes": [],
    "hash": "d15ac94f6b1e4b834930f2d5ac84eb4e8e235d19",
    "gitTags": "",
    "committerDate": "2018-05-09 12:25:29 -0400",
    "isTagged": true,
    "tag": "@pie-lib/text-select@1.1.1"
  },
  {
    "type": "chore",
    "scope": null,
    "subject": "tidy up",
    "merge": null,
    "header": "chore: tidy up",
    "body": null,
    "footer": null,
    "notes": [],
    "hash": "c8268c95d6b521788813e1c0c638991ca94b9dea",
    "gitTags": "",
    "committerDate": "2018-05-08 16:39:24 -0400",
    "isTagged": true,
    "tag": "@pie-lib/text-select@1.1.0"
  },
  {
    "type": "chore",
    "scope": "demo",
    "subject": "fix demo",
    "merge": null,
    "header": "chore(demo): fix demo",
    "body": null,
    "footer": null,
    "notes": [],
    "hash": "e5d0f8a0c6044d52710326f6c480b0dc77570577",
    "gitTags": "",
    "committerDate": "2018-05-08 16:38:55 -0400",
    "isTagged": true,
    "tag": "@pie-lib/text-select@1.1.0"
  },
  {
    "type": "chore",
    "scope": null,
    "subject": "clean up",
    "merge": null,
    "header": "chore: clean up",
    "body": null,
    "footer": null,
    "notes": [],
    "hash": "8cb1e415bb43a0f3109a8efef95a8c4181e71e5c",
    "gitTags": "",
    "committerDate": "2018-05-08 16:32:55 -0400",
    "isTagged": true,
    "tag": "@pie-lib/text-select@1.1.0"
  },
  {
    "type": "feat",
    "scope": "text-select",
    "subject": "Add new text-select package.",
    "merge": null,
    "header": "feat(text-select): Add new text-select package.",
    "body": "Features:\n* `TextSelect`\n* `TokenSelect`\n* `Tokenizer`",
    "footer": null,
    "notes": [],
    "hash": "3916c1922fa8ab3fe5a58cf35147f73f42d96f7e",
    "gitTags": "",
    "committerDate": "2018-05-08 16:28:33 -0400",
    "isTagged": true,
    "tag": "@pie-lib/text-select@1.1.0"
  },
  {
    "type": "fix",
    "scope": "text-select",
    "subject": "making use of span wrapper for tokens only where needed and recreated the html as string (issue: previous implementation was breaking the html content)",
    "merge": null,
    "header": "fix(text-select): making use of span wrapper for tokens only where needed and recreated the html as string (issue: previous implementation was breaking the html content)",
    "body": null,
    "footer": null,
    "notes": [],
    "hash": "532adc78de6cb429a521969e2ed9dd4f22f774fd",
    "gitTags": "",
    "committerDate": "2019-03-28 13:14:54 +0200",
    "isTagged": true,
    "tag": "@pie-lib/text-select@1.4.10"
  },
  {
    "type": "feat",
    "scope": null,
    "subject": "version bumps",
    "merge": null,
    "header": "feat: version bumps",
    "body": null,
    "footer": null,
    "notes": [],
    "hash": "23eb54f95e4b6480e2f8c5b336627a7f3bc2f428",
    "gitTags": "",
    "committerDate": "2019-06-10 15:24:32 +0100",
    "isTagged": true,
    "tag": "@pie-lib/text-select@1.5.0"
  },
  {
    "type": "chore",
    "scope": "merge",
    "subject": "merged master into this branch",
    "merge": null,
    "header": "chore(merge): merged master into this branch",
    "body": null,
    "footer": null,
    "notes": [],
    "hash": "e7758d577c82c0f39a5bf44556792517cd1ea6b0",
    "gitTags": "",
    "committerDate": "2019-07-02 11:29:52 -0400",
    "isTagged": true,
    "tag": "@pie-lib/text-select@1.5.2"
  },
  {
    "type": "fix",
    "scope": null,
    "subject": "ch5389: A Select Text item had incorrect text if some of the tokens were defined twice, because in the normalized array there were being added tokens where start value was bigger than the end value of the token.",
    "merge": null,
    "header": "fix: ch5389: A Select Text item had incorrect text if some of the tokens were defined twice, because in the normalized array there were being added tokens where start value was bigger than the end value of the token.",
    "body": null,
    "footer": null,
    "notes": [],
    "hash": "75ab455778ff5b4fd106526aada329228208570d",
    "gitTags": " (origin/andreea/ch5389/a-select-text-item-has-incorrect-text-apparently)",
    "committerDate": "2019-12-05 14:42:22 +0200",
    "isTagged": true,
    "tag": "@pie-lib/text-select@1.5.6"
  },
  {
    "type": "fix",
    "scope": null,
    "subject": "add module prop to package.json",
    "merge": null,
    "header": "fix: add module prop to package.json",
    "body": null,
    "footer": null,
    "notes": [],
    "hash": "946c11820a49ae1dd76ba3b2809f0c4bb99dd0d4",
    "gitTags": "",
    "committerDate": "2020-03-30 13:03:59 +0100",
    "isTagged": true,
    "tag": "@pie-lib/text-select@1.5.11"
  },
  {
    "type": "fix",
    "scope": null,
    "subject": "correct export syntax",
    "merge": null,
    "header": "fix: correct export syntax",
    "body": null,
    "footer": null,
    "notes": [],
    "hash": "db7fcc0fa1bddf9fc2d304978941db04001ec0ab",
    "gitTags": "",
    "committerDate": "2020-03-30 22:30:10 +0100",
    "isTagged": true,
    "tag": "@pie-lib/text-select@1.5.13"
  },
  {
    "type": "fix",
    "scope": null,
    "subject": "PD-19: Sentence parser was not working properly - updated the package version.",
    "merge": null,
    "header": "fix: PD-19: Sentence parser was not working properly - updated the package version.",
    "body": null,
    "footer": null,
    "notes": [],
    "hash": "057a88e17603f9d393b8f16c94904d65f9b404b7",
    "gitTags": "",
    "committerDate": "2020-04-21 13:09:37 +0300",
    "isTagged": true,
    "tag": "@pie-lib/text-select@1.5.23"
  },
  {
    "type": "feat",
    "scope": "text-select",
    "subject": "color theme support - use wider palette",
    "merge": null,
    "header": "feat(text-select): color theme support - use wider palette",
    "body": null,
    "footer": null,
    "notes": [],
    "hash": "2918cdd98d46dd2822950c19445608d8abf6c4cc",
    "gitTags": " (origin/feat/colors)",
    "committerDate": "2020-10-06 20:44:23 +0300",
    "isTagged": true,
    "tag": "@pie-lib/text-select@1.6.0"
  },
  {
    "type": "feat",
    "scope": "text-select",
    "subject": "add color theme support",
    "merge": null,
    "header": "feat(text-select): add color theme support",
    "body": null,
    "footer": null,
    "notes": [],
    "hash": "8dd94e8206b9277a077b0e6c40954ab4b9428146",
    "gitTags": "",
    "committerDate": "2020-09-24 18:50:27 +0300",
    "isTagged": true,
    "tag": "@pie-lib/text-select@1.6.0"
  },
  {
    "type": "feat",
    "scope": "text-select",
    "subject": "fix default colors in theme for hover and select",
    "merge": null,
    "header": "feat(text-select): fix default colors in theme for hover and select",
    "body": null,
    "footer": null,
    "notes": [],
    "hash": "f85b8f9585c11389ae0182632cc41d4cd5c082ee",
    "gitTags": " (origin/feat/color-support)",
    "committerDate": "2020-10-26 14:01:51 +0200",
    "isTagged": true,
    "tag": "@pie-lib/text-select@1.7.0"
  },
  {
    "type": "fix",
    "scope": "select-text",
    "subject": "fix text indent styling for tokens",
    "merge": null,
    "header": "fix(select-text): fix text indent styling for tokens",
    "body": null,
    "footer": null,
    "notes": [],
    "hash": "0d13170e2c2daf67ccb9b6ae80cc9223368581a9",
    "gitTags": " (origin/feat/color-support)",
    "committerDate": "2020-10-26 15:30:32 +0200",
    "isTagged": true,
    "tag": "@pie-lib/text-select@1.7.1"
  },
  {
    "type": "fix",
    "scope": null,
    "subject": "Added fix for style changes after selection of max tokens PD-646",
    "merge": null,
    "header": "fix: Added fix for style changes after selection of max tokens PD-646",
    "body": null,
    "footer": null,
    "notes": [],
    "hash": "30183a9aa2524d3487bb2124f6cc487f3f8cefd3",
    "gitTags": "",
    "committerDate": "2020-11-17 13:47:26 +0530",
    "isTagged": true,
    "tag": "@pie-lib/text-select@1.7.3"
  },
  {
    "type": "fix",
    "scope": "text-select",
    "subject": "fix token rendering issue - PD-642",
    "merge": null,
    "header": "fix(text-select): fix token rendering issue - PD-642",
    "body": null,
    "footer": null,
    "notes": [],
    "hash": "89f3b709b9b1732e6a71ae3aa411d547b7166ac0",
    "gitTags": " (origin/fix/PD-642-line-breaks)",
    "committerDate": "2021-01-18 14:18:09 +0200",
    "isTagged": true,
    "tag": "@pie-lib/text-select@1.7.4"
  },
  {
    "type": "fix",
    "scope": "text-select",
    "subject": "fix space between lines",
    "merge": null,
    "header": "fix(text-select): fix space between lines",
    "body": null,
    "footer": null,
    "notes": [],
    "hash": "56335373404f08cac617845a19b68b3c5018debd",
    "gitTags": " (origin/fix/text-select-add-line-height)",
    "committerDate": "2021-02-02 12:16:28 +0200",
    "isTagged": true,
    "tag": "@pie-lib/text-select@1.7.10"
  },
  {
    "type": "fix",
    "scope": "text-select",
    "subject": "fix layout for legacy items with line number",
    "merge": null,
    "header": "fix(text-select): fix layout for legacy items with line number",
    "body": null,
    "footer": null,
    "notes": [],
    "hash": "d50865ee7705c3889ec366ada54810334114fbe5",
    "gitTags": " (origin/fix/select-text-with-line-number)",
    "committerDate": "2021-02-25 13:53:20 +0200",
    "isTagged": true,
    "tag": "@pie-lib/text-select@1.7.12"
  },
  {
    "type": "fix",
    "scope": "text-select",
    "subject": "show tokens if they are selected in view mode to fix PD-464",
    "merge": null,
    "header": "fix(text-select): show tokens if they are selected in view mode to fix PD-464",
    "body": null,
    "footer": null,
    "notes": [],
    "hash": "7821536264b822852b12caefcea7b5d84f4c4f03",
    "gitTags": "",
    "committerDate": "2021-02-24 16:38:15 +0200",
    "isTagged": true,
    "tag": "@pie-lib/text-select@1.7.12"
  },
  {
    "type": "fix",
    "scope": "text-select",
    "subject": "fix padding for tokens in order to fix PD-860",
    "merge": null,
    "header": "fix(text-select): fix padding for tokens in order to fix PD-860",
    "body": null,
    "footer": null,
    "notes": [],
    "hash": "eacb81c1f28276b95c75a203515c7c041df39ee7",
    "gitTags": " (origin/fix/select-text-token-padding)",
    "committerDate": "2021-02-23 16:03:46 +0200",
    "isTagged": true,
    "tag": "@pie-lib/text-select@1.7.12"
  },
  {
    "type": "feat",
    "scope": "text-select",
    "subject": "when select-text item permits only one selection, change behavior of gather PD-958",
    "merge": null,
    "header": "feat(text-select): when select-text item permits only one selection, change behavior of gather PD-958",
    "body": null,
    "footer": null,
    "notes": [],
    "hash": "c1813148b652839635cb67882abeda78c3855235",
    "gitTags": "",
    "committerDate": "2021-05-25 13:31:19 +0300",
    "isTagged": true,
    "tag": "@pie-lib/text-select@1.8.0"
  },
  {
    "type": "fix",
    "scope": "text-select",
    "subject": "fix incorrect indenting PD-1038",
    "merge": null,
    "header": "fix(text-select): fix incorrect indenting PD-1038",
    "body": null,
    "footer": null,
    "notes": [],
    "hash": "4d56509d3411c160328febaafc023aa83ad6e081",
    "gitTags": " (origin/fix/PD-1038/select-text-fix-indentation)",
    "committerDate": "2021-05-20 13:54:09 +0300",
    "isTagged": true,
    "tag": "@pie-lib/text-select@1.8.0"
  },
  {
    "type": "fix",
    "scope": "text-select",
    "subject": "select text view mode should use black for text color PD-1154",
    "merge": null,
    "header": "fix(text-select): select text view mode should use black for text color PD-1154",
    "body": null,
    "footer": null,
    "notes": [],
    "hash": "0db5b1e47b48a9eb3669eea2a1bcfb4eba27f820",
    "gitTags": " (origin/fix/PD-1154/select-text-view-mode-text-color)",
    "committerDate": "2021-05-18 12:04:39 +0300",
    "isTagged": true,
    "tag": "@pie-lib/text-select@1.8.0"
  },
  {
    "type": "fix",
    "scope": "text-select",
    "subject": "Fixed white space collapse PD-477",
    "merge": null,
    "header": "fix(text-select): Fixed white space collapse PD-477",
    "body": null,
    "footer": null,
    "notes": [],
    "hash": "1f9481fac827045491b8d4f827da944cfcd0a7b3",
    "gitTags": " (origin/fix/PD-477)",
    "committerDate": "2021-07-22 12:12:59 +0300",
    "isTagged": true,
    "tag": "@pie-lib/text-select@1.8.3"
  }
]