[
  {
    "type": "fix",
    "scope": null,
    "subject": "rm child prepack in favour of root prepack",
    "merge": null,
    "header": "fix: rm child prepack in favour of root prepack",
    "body": null,
    "footer": null,
    "notes": [],
    "hash": "381d8d6485269b641d8d4655148966d2e70803be",
    "gitTags": "",
    "committerDate": "2019-03-15 09:51:11 +0000",
    "isTagged": true,
    "tag": "@pie-lib/charting@4.0.13"
  },
  {
    "type": "chore",
    "scope": null,
    "subject": "get packages to call changelog function on prepack",
    "merge": null,
    "header": "chore: get packages to call changelog function on prepack",
    "body": null,
    "footer": null,
    "notes": [],
    "hash": "8828f01f2d16d29404ba837c1de40d09e7230ec5",
    "gitTags": "",
    "committerDate": "2019-03-14 12:40:05 +0000",
    "isTagged": true,
    "tag": "@pie-lib/charting@4.0.10"
  },
  {
    "type": "chore",
    "scope": null,
    "subject": "call changelog on prepack",
    "merge": null,
    "header": "chore: call changelog on prepack",
    "body": null,
    "footer": null,
    "notes": [],
    "hash": "b672c012de096c55b765a765f758da3fc5df2f90",
    "gitTags": "",
    "committerDate": "2019-03-13 23:00:44 +0000",
    "isTagged": true,
    "tag": "@pie-lib/charting@4.0.10"
  },
  {
    "type": "chore",
    "scope": null,
    "subject": "generate changelog.json instead of markdown",
    "merge": null,
    "header": "chore: generate changelog.json instead of markdown",
    "body": null,
    "footer": null,
    "notes": [],
    "hash": "eaa5019a11f70c53425d55856bd3b940237f8c7d",
    "gitTags": "",
    "committerDate": "2019-03-13 17:24:09 +0000",
    "isTagged": true,
    "tag": "@pie-lib/charting@4.0.10"
  },
  {
    "type": "fix",
    "scope": null,
    "subject": "force version bump",
    "merge": null,
    "header": "fix: force version bump",
    "body": null,
    "footer": null,
    "notes": [],
    "hash": "dd057a52e90133dfb30660b1824760cb9f10a280",
    "gitTags": "",
    "committerDate": "2019-02-17 21:23:35 +0000",
    "isTagged": true,
    "tag": "@pie-lib/charting@4.0.10"
  },
  {
    "type": "fix",
    "scope": null,
    "subject": "version bump",
    "merge": null,
    "header": "fix: version bump",
    "body": null,
    "footer": null,
    "notes": [],
    "hash": "d1624c88dca15007f39197c022b46467c2501e7a",
    "gitTags": "",
    "committerDate": "2019-01-30 23:00:44 +0000",
    "isTagged": true,
    "tag": "@pie-lib/charting@4.0.10"
  },
  {
    "type": "feat",
    "scope": null,
    "subject": "charting re-write to fit our requirements.",
    "merge": null,
    "header": "feat: charting re-write to fit our requirements.",
    "body": null,
    "footer": "BREAKING CHANGE: This has a number of new components. The old components\nare gone.",
    "notes": [
      {
        "title": "BREAKING CHANGE",
        "text": "This has a number of new components. The old components\nare gone."
      }
    ],
    "hash": "ca5cbf79e2578b23d67f64cbee29c96db2398ff6",
    "gitTags": "",
    "committerDate": "2019-01-30 21:51:02 +0000",
    "isTagged": true,
    "tag": "@pie-lib/charting@4.0.0"
  },
  {
    "type": "fix",
    "scope": null,
    "subject": "rm githead",
    "merge": null,
    "header": "fix: rm githead",
    "body": null,
    "footer": null,
    "notes": [],
    "hash": "a1523aabfe34697970bb94f3ed300603d9e11f74",
    "gitTags": "",
    "committerDate": "2018-09-12 14:44:09 +0100",
    "isTagged": true,
    "tag": "@pie-lib/charting@2.3.5"
  },
  {
    "type": "chore",
    "scope": null,
    "subject": "fix snapshots",
    "merge": null,
    "header": "chore: fix snapshots",
    "body": null,
    "footer": null,
    "notes": [],
    "hash": "e3f81bd7b84a831409bbe10d84c4352b5cc77b2b",
    "gitTags": "",
    "committerDate": "2018-09-12 14:41:45 +0100",
    "isTagged": true,
    "tag": "@pie-lib/charting@2.3.5"
  },
  {
    "type": "fix",
    "scope": null,
    "subject": "githead",
    "merge": null,
    "header": "fix: githead",
    "body": null,
    "footer": null,
    "notes": [],
    "hash": "3e485e0a7094496fd93d86a0500c75e343e9fac2",
    "gitTags": "",
    "committerDate": "2018-09-12 14:38:21 +0100",
    "isTagged": true,
    "tag": "@pie-lib/charting@2.3.5"
  },
  {
    "type": "chore",
    "scope": null,
    "subject": "update shapshots",
    "merge": null,
    "header": "chore: update shapshots",
    "body": null,
    "footer": null,
    "notes": [],
    "hash": "5e32e714d402e153223327badec463607ee0c36f",
    "gitTags": "",
    "committerDate": "2018-06-06 21:10:13 -0400",
    "isTagged": true,
    "tag": "@pie-lib/charting@2.3.2"
  },
  {
    "type": "feature",
    "scope": "graph-lines",
    "subject": "finalized graph lines support for initial functionality including multiple lines",
    "merge": null,
    "header": "feature(graph-lines): finalized graph lines support for initial functionality including multiple lines",
    "body": null,
    "footer": null,
    "notes": [],
    "hash": "3134bdce53a727476abc74d65706597fa9b83649",
    "gitTags": "",
    "committerDate": "2018-06-06 14:36:58 +0300",
    "isTagged": true,
    "tag": "@pie-lib/charting@2.3.1"
  },
  {
    "type": "fix",
    "scope": "lineUtils",
    "subject": "pointsFromExpression calculate using when x and y are 0",
    "merge": null,
    "header": "fix(lineUtils): pointsFromExpression calculate using when x and y are 0",
    "body": null,
    "footer": null,
    "notes": [],
    "hash": "d641fcd3824c539006b3c09b087e2106f2a7e646",
    "gitTags": "",
    "committerDate": "2018-06-04 12:44:10 -0400",
    "isTagged": true,
    "tag": "@pie-lib/charting@2.3.1"
  },
  {
    "type": "feature",
    "scope": "graph-lines",
    "subject": "line utils logic extended and graph line component fixes",
    "merge": null,
    "header": "feature(graph-lines): line utils logic extended and graph line component fixes",
    "body": null,
    "footer": null,
    "notes": [],
    "hash": "6c3def4004c8f3f14ab08762332764c3641cc767",
    "gitTags": "",
    "committerDate": "2018-06-04 16:53:49 +0300",
    "isTagged": true,
    "tag": "@pie-lib/charting@2.3.1"
  },
  {
    "type": "fix",
    "scope": "expression",
    "subject": "handle vertical lines which have no slope",
    "merge": null,
    "header": "fix(expression): handle vertical lines which have no slope",
    "body": null,
    "footer": null,
    "notes": [],
    "hash": "2cd6bb0c039ca9e8eb568ee4377b8a17e6234207",
    "gitTags": "",
    "committerDate": "2018-05-28 15:36:46 -0400",
    "isTagged": true,
    "tag": "@pie-lib/charting@2.3.0"
  },
  {
    "type": "feat",
    "scope": null,
    "subject": "add Expression.equals method",
    "merge": null,
    "header": "feat: add Expression.equals method",
    "body": null,
    "footer": null,
    "notes": [],
    "hash": "5ae0c1ee14e16d6d7af316d6a8f9922fc13660e6",
    "gitTags": " (origin/feature/charting-line-utils)",
    "committerDate": "2018-05-25 13:10:31 -0400",
    "isTagged": true,
    "tag": "@pie-lib/charting@2.3.0"
  },
  {
    "type": "chore",
    "scope": null,
    "subject": "snapshots update",
    "merge": null,
    "header": "chore: snapshots update",
    "body": null,
    "footer": null,
    "notes": [],
    "hash": "72b2dc6260952e4a3937609c2c7a3ef4a59dc371",
    "gitTags": "",
    "committerDate": "2018-05-15 13:41:08 -0400",
    "isTagged": true,
    "tag": "@pie-lib/charting@2.2.3"
  },
  {
    "type": "fix",
    "scope": "lint",
    "subject": "lint fixes",
    "merge": null,
    "header": "fix(lint): lint fixes",
    "body": null,
    "footer": null,
    "notes": [],
    "hash": "f0595831a75561d829c0f18f86ce5ea7feeb4ddd",
    "gitTags": "",
    "committerDate": "2018-05-09 13:35:42 -0400",
    "isTagged": true,
    "tag": "@pie-lib/charting@2.2.1"
  },
  {
    "type": "feat",
    "scope": "dependencies",
    "subject": "version bump",
    "merge": null,
    "header": "feat(dependencies): version bump",
    "body": null,
    "footer": null,
    "notes": [],
    "hash": "31bd3b3747d3808bc4f85208073331d7176e9107",
    "gitTags": "",
    "committerDate": "2018-04-24 09:41:05 -0400",
    "isTagged": true,
    "tag": "@pie-lib/charting@2.2.0"
  },
  {
    "type": "chore",
    "scope": "tests",
    "subject": "fix tests",
    "merge": null,
    "header": "chore(tests): fix tests",
    "body": null,
    "footer": null,
    "notes": [],
    "hash": "b23b2b70c5852ec6e34f2b6b06deed84bbf308ec",
    "gitTags": "",
    "committerDate": "2018-04-23 21:50:37 -0400",
    "isTagged": true,
    "tag": "@pie-lib/charting@2.2.0"
  },
  {
    "type": "feat",
    "scope": "point-intercept",
    "subject": "add title label to top of chart",
    "merge": null,
    "header": "feat(point-intercept): add title label to top of chart",
    "body": null,
    "footer": null,
    "notes": [],
    "hash": "71ba936432a8d60b5d14969874c90691d981b3c4",
    "gitTags": "",
    "committerDate": "2018-04-23 09:42:15 -0400",
    "isTagged": true,
    "tag": "@pie-lib/charting@2.1.0"
  },
  {
    "type": "fix",
    "scope": "dependencies",
    "subject": "use react 16 and latest material-ui",
    "merge": null,
    "header": "fix(dependencies): use react 16 and latest material-ui",
    "body": null,
    "footer": "BREAKING CHANGE: react@^16.3.1 is required as a dependency.",
    "notes": [
      {
        "title": "BREAKING CHANGE",
        "text": "react@^16.3.1 is required as a dependency."
      }
    ],
    "hash": "2ac4f97d5a32d391eacdba48a6bb9e020ac6586b",
    "gitTags": "",
    "committerDate": "2018-04-12 22:43:29 -0400",
    "isTagged": true,
    "tag": "@pie-lib/charting@1.0.0"
  },
  {
    "type": "feat",
    "scope": "charting",
    "subject": "new charting package",
    "merge": null,
    "header": "feat(charting): new charting package",
    "body": null,
    "footer": null,
    "notes": [],
    "hash": "97c2f60e32a8fe3e0797aef5cf7b5b9dcb83edb3",
    "gitTags": "",
    "committerDate": "2018-04-02 10:15:10 -0400",
    "isTagged": true,
    "tag": "@pie-lib/charting@0.1.0"
  },
  {
    "type": "feat",
    "scope": null,
    "subject": "version bumps",
    "merge": null,
    "header": "feat: version bumps",
    "body": null,
    "footer": null,
    "notes": [],
    "hash": "23eb54f95e4b6480e2f8c5b336627a7f3bc2f428",
    "gitTags": "",
    "committerDate": "2019-06-10 15:24:32 +0100",
    "isTagged": true,
    "tag": "@pie-lib/charting@4.1.0"
  },
  {
    "type": "feat",
    "scope": "charting",
    "subject": "added Line with Crosses Chart Type. Add rotation on categories name if they do not fit. Fixed issue with editing category name.",
    "merge": null,
    "header": "feat(charting): added Line with Crosses Chart Type. Add rotation on categories name if they do not fit. Fixed issue with editing category name.",
    "body": null,
    "footer": null,
    "notes": [],
    "hash": "ae5889313db53a6abcba4a20a58fdd00f60d74d8",
    "gitTags": "",
    "committerDate": "2019-08-03 18:38:43 +0300",
    "isTagged": true,
    "tag": "@pie-lib/charting@4.2.0"
  },
  {
    "type": "feat",
    "scope": "charting",
    "subject": "Add/remove categories, edit categories, interactive category, calculate step if it is not defined.",
    "merge": null,
    "header": "feat(charting): Add/remove categories, edit categories, interactive category, calculate step if it is not defined.",
    "body": null,
    "footer": null,
    "notes": [],
    "hash": "48520a7a4842b8b9860ff81b8764f4d3442a5a7d",
    "gitTags": "",
    "committerDate": "2019-07-30 14:00:20 +0300",
    "isTagged": true,
    "tag": "@pie-lib/charting@4.2.0"
  },
  {
    "type": "feat",
    "scope": null,
    "subject": "Added interactive (user can drag to change category value) and deletable (delete category) properties.",
    "merge": null,
    "header": "feat: Added interactive (user can drag to change category value) and deletable (delete category) properties.",
    "body": null,
    "footer": null,
    "notes": [],
    "hash": "b3b5377215b7715f1fa5a8a9578772d41de2a543",
    "gitTags": "",
    "committerDate": "2019-07-29 11:11:17 +0300",
    "isTagged": true,
    "tag": "@pie-lib/charting@4.2.0"
  },
  {
    "type": "feat",
    "scope": "charting",
    "subject": "Added Dot Plot chart type and Line Plot chart type. (WIP)",
    "merge": null,
    "header": "feat(charting): Added Dot Plot chart type and Line Plot chart type. (WIP)",
    "body": null,
    "footer": null,
    "notes": [],
    "hash": "b9cafc3356447b3ec55aeaedb47dbd867173e544",
    "gitTags": "",
    "committerDate": "2019-07-23 16:46:51 +0300",
    "isTagged": true,
    "tag": "@pie-lib/charting@4.2.0"
  },
  {
    "type": "feat",
    "scope": "charting",
    "subject": "Completed Bar chart type, added Histogram chart type and added Line chart type. (WIP)",
    "merge": null,
    "header": "feat(charting): Completed Bar chart type, added Histogram chart type and added Line chart type. (WIP)",
    "body": null,
    "footer": null,
    "notes": [],
    "hash": "271b173448cad8ea9356993cfe60941be01d0c33",
    "gitTags": "",
    "committerDate": "2019-07-22 14:55:31 +0300",
    "isTagged": true,
    "tag": "@pie-lib/charting@4.2.0"
  },
  {
    "type": "fix",
    "scope": null,
    "subject": "add missing dep",
    "merge": null,
    "header": "fix: add missing dep",
    "body": null,
    "footer": null,
    "notes": [],
    "hash": "68170c5ece16d28dceea473af949b1f701065ddb",
    "gitTags": " (develop)",
    "committerDate": "2019-08-27 14:52:29 +0100",
    "isTagged": true,
    "tag": "@pie-lib/charting@4.2.4"
  },
  {
    "type": "fix",
    "scope": null,
    "subject": "raised up in ch5875: Added sanity checks for `size` property.",
    "merge": null,
    "header": "fix: raised up in ch5875: Added sanity checks for `size` property.",
    "body": null,
    "footer": null,
    "notes": [],
    "hash": "82b235277a1845c8f9399e22c8cd697880b9ea25",
    "gitTags": "",
    "committerDate": "2019-12-09 16:09:18 +0200",
    "isTagged": true,
    "tag": "@pie-lib/charting@4.2.5"
  },
  {
    "type": "fix",
    "scope": null,
    "subject": "add module prop to package.json",
    "merge": null,
    "header": "fix: add module prop to package.json",
    "body": null,
    "footer": null,
    "notes": [],
    "hash": "0d81793fdd3ccaafb2750d3844cdded5cb83434f",
    "gitTags": "",
    "committerDate": "2020-03-30 13:00:09 +0100",
    "isTagged": true,
    "tag": "@pie-lib/charting@4.2.10"
  },
  {
    "type": "fix",
    "scope": null,
    "subject": "correct export syntax",
    "merge": null,
    "header": "fix: correct export syntax",
    "body": null,
    "footer": null,
    "notes": [],
    "hash": "b7b6b57e1a56180417db679f215c3bd8d82453f7",
    "gitTags": "",
    "committerDate": "2020-03-30 22:07:39 +0100",
    "isTagged": true,
    "tag": "@pie-lib/charting@4.2.11"
  },
  {
    "type": "feat",
    "scope": "charting",
    "subject": "add color theme support",
    "merge": null,
    "header": "feat(charting): add color theme support",
    "body": null,
    "footer": null,
    "notes": [],
    "hash": "606d45e46f86cb8f56544befdb8b71fb8a451746",
    "gitTags": "",
    "committerDate": "2020-09-29 16:53:15 +0300",
    "isTagged": true,
    "tag": "@pie-lib/charting@4.3.0"
  },
  {
    "type": "fix",
    "scope": null,
    "subject": "bad src import",
    "merge": null,
    "header": "fix: bad src import",
    "body": null,
    "footer": null,
    "notes": [],
    "hash": "a2d16abff04cbb118699113260de76d5a5ac45e5",
    "gitTags": " (origin/feat/colors)",
    "committerDate": "2020-10-08 10:38:03 +0100",
    "isTagged": true,
    "tag": "@pie-lib/charting@4.3.1"
  }
]